AuthVault/AuthVault.py
AuthVault/__init__.py
AuthVault-3.0.1.dist-info/METADATA
AuthVault-3.0.1.dist-info/WHEEL
AuthVault-3.0.1.dist-info/top_level.txt
AuthVault-3.0.1.dist-info/RECORD
