Metadata-Version: 2.1
Name: AuthVault
Version: 3.0.1
Home-page: 
Author: QSXD
Author-email: n3v1n22@gmail.com
Classifier: Programming Language :: Python :: 3
Classifier: License :: OSI Approved :: MIT License
Classifier: Operating System :: OS Independent
Requires-Dist: requests
Requires-Dist: gspread
Requires-Dist: oauth2client
Requires-Dist: cryptography
Requires-Dist: psutil
Requires-Dist: pyarmor
